pyAnimals_ejh/__init__.py
pyAnimals_ejh/pyAnimals_ejh.py
tests/__init__.py
tests/test_clear_screen.py
tests/test_get_animal.py
tests/test_get_random_fact.py
tests/test_get_random_message.py
tests/test_move.py
tests/test_printMessage.py
tests/test_print_fact.py
tests/test_race.py
tests/test_randMessage.py
pyAnimals_ejh-0.2.1.dist-info/LICENSE
pyAnimals_ejh-0.2.1.dist-info/METADATA
pyAnimals_ejh-0.2.1.dist-info/WHEEL
pyAnimals_ejh-0.2.1.dist-info/top_level.txt
pyAnimals_ejh-0.2.1.dist-info/RECORD
