Metadata-Version: 2.1
Name: pyAnimals_ejh
Version: 0.2.1
Summary: A fun package that displays animals on the terminal with movement and messages.
Home-page: https://github.com/software-students-fall2024/3-python-package-ejh
Author: Emma Zhu, Haley Hobbs, Jason Tran, Jenna Han
Author-email: egz2006@nyu.edu, hkh9725@nyu.edu, ht2354@nyu.edu, jh7765@nyu.edu
Classifier: Programming Language :: Python :: 3
Classifier: License :: OSI Approved :: MIT License
Classifier: Operating System :: OS Independent
Requires-Python: >=3.6
License-File: LICENSE
